hydratokengen/__init__.py
hydratokengen/cache.py
hydratokengen/exceptions.py
hydratokengen/generator.py
hydratokengen-0.1.0.dist-info/LICENSE
hydratokengen-0.1.0.dist-info/WHEEL
hydratokengen-0.1.0.dist-info/METADATA
hydratokengen-0.1.0.dist-info/RECORD
