Metadata-Version: 2.1
Name: hydratokengen
Version: 0.1.0
Summary: 
Home-page: https://github.com/reciprocity/hydratokengen
Keywords: hydra,jwt
Author: Luka Zakrajšek
Author-email: luka@bancek.net
Requires-Python: >=3.7,<4.0
Classifier: Programming Language :: Python :: 3
Classifier: Programming Language :: Python :: 3.10
Classifier: Programming Language :: Python :: 3.7
Classifier: Programming Language :: Python :: 3.8
Classifier: Programming Language :: Python :: 3.9
Requires-Dist: ory-hydra-client (>=1.10.6,<2.0.0)
Requires-Dist: requests (>=2.26.0,<3.0.0)
Project-URL: Repository, https://github.com/reciprocity/hydratokengen
